sdf_timing/.gitignore
sdf_timing/__init__.py
sdf_timing/__main__.py
sdf_timing/sdflex.py
sdf_timing/sdfparse.py
sdf_timing/sdfwrite.py
sdf_timing/sdfyacc.py
sdf_timing/utils.py
sdf_timing/version.py
sdf_timing/tests/parse_all_test.py
sdf_timing/tests/data/bigchip.sdf
sdf_timing/tests/data/celltype.sdf
sdf_timing/tests/data/clb.sdf
sdf_timing/tests/data/empty.sdf
sdf_timing/tests/data/escaped_name.sdf
sdf_timing/tests/data/fixpoint.sdf
sdf_timing/tests/data/modulo6.sdf
sdf_timing/tests/data/real_triple.sdf
sdf_timing/tests/data/spec-example1.sdf
sdf_timing/tests/data/spec-example2.sdf
sdf_timing/tests/data/spec-example3.sdf
sdf_timing/tests/data/spec-example4.sdf
sdf_timing/tests/data/test-device.sdf
sdf_timing/tests/data/test1.sdf
sdf_timing/tests/data/timings_hx1k.sdf
sdf_timing/tests/data/golden/bigchip.sdf
sdf_timing/tests/data/golden/celltype.sdf
sdf_timing/tests/data/golden/clb.sdf
sdf_timing/tests/data/golden/empty.sdf
sdf_timing/tests/data/golden/escaped_name.sdf
sdf_timing/tests/data/golden/fixpoint.sdf
sdf_timing/tests/data/golden/modulo6.sdf
sdf_timing/tests/data/golden/real_triple.sdf
sdf_timing/tests/data/golden/spec-example1.sdf
sdf_timing/tests/data/golden/spec-example2.sdf
sdf_timing/tests/data/golden/spec-example3.sdf
sdf_timing/tests/data/golden/spec-example4.sdf
sdf_timing/tests/data/golden/test-device.sdf
sdf_timing/tests/data/golden/test1.sdf
sdf_timing/tests/data/golden/timings_hx1k.sdf
sdf_timing-0.0.post131.dist-info/LICENSE
sdf_timing-0.0.post131.dist-info/METADATA
sdf_timing-0.0.post131.dist-info/WHEEL
sdf_timing-0.0.post131.dist-info/entry_points.txt
sdf_timing-0.0.post131.dist-info/top_level.txt
sdf_timing-0.0.post131.dist-info/RECORD
