Metadata-Version: 2.1
Name: sdf-timing
Version: 0.0.post131
Summary: Python library for working Standard Delay Format                 (SDF) Timing Annotation files.
Home-page: https://github.com/chipsalliance/python-sdf-timing
Author: F4PGA Authors
Author-email: f4pga-wg@lists.chipsalliance.org
License: Apache-2.0
Classifier: Programming Language :: Python :: 3
Classifier: License :: OSI Approved :: Apache Software License
Classifier: Operating System :: OS Independent
Requires-Python: >=3.6
License-File: LICENSE
Requires-Dist: ply
Requires-Dist: pyjson
